vitessce/__init__.py
vitessce/config.py
vitessce/config_converter.py
vitessce/constants.py
vitessce/export.py
vitessce/file_def_utils.py
vitessce/repr.py
vitessce/responses.py
vitessce/routes.py
vitessce/utils.py
vitessce/widget.py
vitessce/wrappers.py
vitessce/data_utils/__init__.py
vitessce/data_utils/anndata.py
vitessce/data_utils/entities.py
vitessce/data_utils/multivec.py
vitessce/data_utils/ome.py
vitessce/data_utils/spatialdata_points_zorder.py
vitessce/widget_plugins/__init__.py
vitessce/widget_plugins/demo_plugin.py
vitessce/widget_plugins/spatial_query.py
vitessce-3.8.0.dist-info/METADATA
vitessce-3.8.0.dist-info/WHEEL
vitessce-3.8.0.dist-info/licenses/LICENSE
vitessce-3.8.0.dist-info/RECORD
