Metadata-Version: 2.4
Name: vitessce
Version: 3.8.0
Summary: Jupyter widget facilitating interactive visualization of spatial single-cell data with Vitessce
Project-URL: repository, https://github.com/vitessce/vitessce-python
Author-email: Mark Keller <mark_keller@hms.harvard.edu>
License: MIT License
License-File: LICENSE
Keywords: ipython,jupyter,widgets
Classifier: Development Status :: 4 - Beta
Classifier: Framework :: IPython
Classifier: Intended Audience :: Developers
Classifier: Intended Audience :: Science/Research
Classifier: Programming Language :: Python :: 3.9
Classifier: Programming Language :: Python :: 3.10
Classifier: Programming Language :: Python :: 3.11
Classifier: Programming Language :: Python :: 3.12
Classifier: Topic :: Multimedia :: Graphics
Requires-Python: >=3.10
Requires-Dist: black>=21.11b1
Requires-Dist: numcodecs<0.16.0,>=0.5.7
Requires-Dist: numpy>=1.21.2
Requires-Dist: pandas>=1.1.2
Requires-Dist: scipy>=1.2.1
Requires-Dist: zarr<3,>=2.5.0
Provides-Extra: all
Requires-Dist: aiofiles>=0.6.0; extra == 'all'
Requires-Dist: anndata>=0.7.8; extra == 'all'
Requires-Dist: anywidget>=0.9.10; extra == 'all'
Requires-Dist: fsspec; extra == 'all'
Requires-Dist: generate-tiff-offsets>=0.1.9; extra == 'all'
Requires-Dist: jupyter-server-proxy>=1.5.2; extra == 'all'
Requires-Dist: kerchunk>=0.2.6; extra == 'all'
Requires-Dist: negspy>=0.2.24; extra == 'all'
Requires-Dist: ome-zarr<0.10.3; extra == 'all'
Requires-Dist: oxc-py>=0.1.1; extra == 'all'
Requires-Dist: scanpy>=1.10.2; extra == 'all'
Requires-Dist: starlette>=0.14.0; extra == 'all'
Requires-Dist: tifffile>=2020.10.1; extra == 'all'
Requires-Dist: ujson>=4.0.1; extra == 'all'
Requires-Dist: uvicorn>=0.17.0; extra == 'all'
Provides-Extra: building
Provides-Extra: demos
Requires-Dist: pulp==2.7.0; extra == 'demos'
Requires-Dist: pyyaml; extra == 'demos'
Requires-Dist: snakemake; extra == 'demos'
Provides-Extra: dev
Provides-Extra: docs
Requires-Dist: jinja2; extra == 'docs'
Requires-Dist: nbclean==0.3.2; extra == 'docs'
Requires-Dist: nbconvert>=6.2; extra == 'docs'
Requires-Dist: nbsphinx==0.8.8; extra == 'docs'
Requires-Dist: sphinx-rtd-theme==1.0.0; extra == 'docs'
Requires-Dist: sphinx==4.2.0; extra == 'docs'
Requires-Dist: sphinxcontrib-applehelp==1.0.4; extra == 'docs'
Requires-Dist: sphinxcontrib-devhelp==1.0.2; extra == 'docs'
Requires-Dist: sphinxcontrib-htmlhelp==2.0.1; extra == 'docs'
Requires-Dist: sphinxcontrib-jsmath==1.0.1; extra == 'docs'
Requires-Dist: sphinxcontrib-qthelp==1.0.3; extra == 'docs'
Requires-Dist: sphinxcontrib-serializinghtml==1.1.5; extra == 'docs'
Requires-Dist: sqlalchemy==1.3.24; extra == 'docs'
Provides-Extra: linting
Provides-Extra: notebook
Requires-Dist: dask[dataframe]==2024.11.1; extra == 'notebook'
Requires-Dist: marimo; extra == 'notebook'
Requires-Dist: spatialdata>=0.3.0; extra == 'notebook'
Requires-Dist: starlette>=0.42.0; extra == 'notebook'
Requires-Dist: tqdm>=4.1.0; extra == 'notebook'
Provides-Extra: testing
